{
    "sourceFile": ".history/resources/views/pages/frontend/accueil.blade_20241128102808.php",
    "activeCommit": 0,
    "commits": [
        {
            "activePatchIndex": 0,
            "patches": [
                {
                    "date": 1732797138518,
                    "content": "Index: \n===================================================================\n--- \n+++ \n"
                }
            ],
            "date": 1732797138518,
            "name": "Commit-0",
            "content": "<x-guest-layout>\n    <x-preloader/>\n\n    <x-header-guest/>\n    <hr class=\" w-full h-0.5 bg-white\">\n\n    <!-- Slider Area -->\n    <section class=\"slider\">\n        <div class=\"hero-slider\">\n            @php\n                $slides = [\n                    \n                    ['image' => 'images/caroussel/caroussel8.jpg', 'title' => 'MU-POl, la Mutuelle de la Police Nationale', 'text_color' => 'white'],\n                    ['image' => 'images/caroussel/caroussel10.JPG', 'title' => 'MU-POl, la Mutuelle de la Police Nationale', 'text_color' => 'white'],\n\n                ];\n            @endphp\n        \n    \n            @foreach ($slides as $slide)\n            <!-- Start Single Slider -->\n            <div class=\"container\">\n                <div class=\"single-slider !p-4\" style=\"background-image:url('{{ $slide['image'] }}')\">\n                    <div class=\"row\">\n                        <div class=\"col-lg-7 !p-2\">\n                            <div class=\"text text-stroke-200 bg-gray-700 bg-opacity-50 \">\n                                <h1 class=\"{{ $slide['text_color'] === 'white' ? 'text-white' : 'text-black' }}\">\n                                    {{ $slide['title'] }}\n                                </h1>\n                                <p class=\"{{ $slide['text_color'] === 'white' ? 'text-white' : 'text-black' }}\" >Tous solidaires pour notre bien-être!</p>\n                                <p class=\"{{ $slide['text_color'] === 'white' ? 'text-white' : 'text-black' }}\">Je suis policier (ère), j&apos;adhère ! Pour le bien-être des membres de ma famille (conjoint, enfants), je les adhère ! </p>\n        \n                                <div class=\"button\">\n                                    <a class=\"btn\" href=\"{{ route('formulaire-adhesion') }}\">\n                                        Adhérer maintenant\n                                    </a>\n                                    <a href=\"#\" class=\"btn primary\">A propos de nous</a>\n                                </div>\n                            </div>\n                        </div>\n                    </div>\n                </div>\n            </div>\n            <!-- End Single Slider -->\n        @endforeach\n        \n        </div>\n    </section>\n    \n    <!--/ End Slider Area -->\n    \n    <!-- Start Schedule Area -->\n    <section class=\"schedule\">\n        <div class=\"container\">\n            <div class=\"schedule-inner\">\n                <div class=\"row  !-m-1\"> \n                    @php\n                        $services = [\n                           \n                       \n                        [\n                            'icon' => 'icofont-hospital',\n                            'title' => 'Hôpitaux Partenaires',\n                            'subtitle' => 'Soins spécialisés',\n                            'description' => 'Nos hôpitaux partenaires offrent une gamme de soins spécialisés pour nos adhérents, avec une couverture partielle des frais hospitaliers.',\n                            'link' => '#',\n                            'link_text' => 'EN SAVOIR PLUS'\n                        ],\n                        [\n                            'icon' => 'icofont-hospital',\n                            'title' => 'Cliniques Partenaires',\n                            'subtitle' => 'Soins de proximité',\n                            'description' => 'Nos cliniques partenaires offrent des soins de proximité, y compris des consultations et des traitements de courte durée, accessibles à nos adhérents.',\n                            'link' => '#',\n                            'link_text' => 'EN SAVOIR PLUS'\n                        ],\n                        [\n                            'icon' => 'icofont-medical-sign',\n                            'title' => 'Pharmacies Partenaires',\n                            'subtitle' => 'Médicaments à prix réduits',\n                            'description' => 'Nous avons des partenariats avec des pharmacies locales qui offrent des médicaments à prix réduits pour nos adhérents.',\n                            'link' => '#',\n                            'link_text' => 'EN SAVOIR PLUS'\n                        ],\n                        ];\n                        \n                    @endphp\n                \n                    @foreach ($services as $service)\n                        <div class=\"col-lg-4 col-md-6 col-12\">\n                            <!-- single-schedule -->\n                            <div class=\"single-schedule\">\n                                <div class=\"inner\">\n                                    <div class=\"icon\">\n                                        <i class=\"{{ $service['icon'] }}\"></i>\n                                    </div>\n                                    <div class=\"single-content\">\n                                        <span>{{ $service['subtitle'] }}</span>\n                                        <h4>{{ $service['title'] }}</h4>\n                                        <p>{{ $service['description'] }}</p>\n                                        <a href=\"{{ $service['link'] }}\">{{ $service['link_text'] }}<i class=\"fa fa-long-arrow-right\"></i></a>\n                                    </div>\n                                </div>\n                            </div>\n                        </div>\n                    @endforeach\n                </div>\n                \n            </div>\n        </div>\n    </section>\n    <!--/End Start schedule Area -->\n\n    {{--  <!-- Start Feautes -->\n    <section class=\"Feautes section\">\n        <div class=\"container\">\n            <div class=\"row\">\n                <div class=\"col-lg-12\">\n                    <div class=\"section-title\">\n                        <h2>Nous sommes toujours prêts à vous aider, vous et votre famille</h2>\n                        <img  class=\"mx-auto\" src=\"{{ asset('images/section-img.png') }}\" alt=\"#\">\n                        <p>La Mutuelle de la Police Nationale vous soutient à chaque étape de votre vie.</p>\n                    </div>\n                </div>\n            </div>\n            <div class=\"row\">\n                <div class=\"col-lg-4 col-12\">\n                    <!-- Start Single features -->\n                    <div class=\"single-features\">\n                        <div class=\"signle-icon\">\n                            <i class=\"icofont icofont-ambulance-cross\"></i>\n                        </div>\n                        <h3>Aide d'urgence</h3>\n                        <p>Intervention rapide pour nos adhérents en cas d'urgence médicale.</p>\n                    </div>\n                    <!-- End Single features -->\n                </div>\n                <div class=\"col-lg-4 col-12\">\n                    <!-- Start Single features -->\n                    <div class=\"single-features\">\n                        <div class=\"signle-icon\">\n                            <i class=\"icofont icofont-medical-sign-alt\"></i>\n                        </div>\n                        <h3>Pharmacie enrichie</h3>\n                        <p>Accès à des médicaments essentiels avec des réductions pour nos membres.</p>\n                    </div>\n                    <!-- End Single features -->\n                </div>\n                <div class=\"col-lg-4 col-12\">\n                    <!-- Start Single features -->\n                    <div class=\"single-features last\">\n                        <div class=\"signle-icon\">\n                            <i class=\"icofont icofont-stethoscope\"></i>\n                        </div>\n                        <h3>Traitement médical</h3>\n                        <p>Des soins adaptés à vos besoins, en toute confiance avec nos médecins partenaires.</p>\n                    </div>\n                    <!-- End Single features -->\n                </div>\n            </div>\n        </div>\n    </section>  --}}\n    \n    <!--/ End Feautes -->\n    \n    {{--  <!-- Start Fun-facts -->\n    <div id=\"fun-facts\" class=\"fun-facts section overlay\">\n        <div class=\"container\">\n            <div class=\"row\">\n                <div class=\"col-lg-3 col-md-6 col-12\">\n                    <!-- Start Single Fun -->\n                    <div class=\"single-fun\">\n                        <i class=\"icofont icofont-home\"></i>\n                        <div class=\"content\">\n                            <span class=\"counter\">3468</span>\n                            <p>Hospital Rooms</p>\n                        </div>\n                    </div>\n                    <!-- End Single Fun -->\n                </div>\n                <div class=\"col-lg-3 col-md-6 col-12\">\n                    <!-- Start Single Fun -->\n                    <div class=\"single-fun\">\n                        <i class=\"icofont icofont-user-alt-3\"></i>\n                        <div class=\"content\">\n                            <span class=\"counter\">557</span>\n                            <p>Specialist Doctors</p>\n                        </div>\n                    </div>\n                    <!-- End Single Fun -->\n                </div>\n                <div class=\"col-lg-3 col-md-6 col-12\">\n                    <!-- Start Single Fun -->\n                    <div class=\"single-fun\">\n                        <i class=\"icofont-simple-smile\"></i>\n                        <div class=\"content\">\n                            <span class=\"counter\">4379</span>\n                            <p>Happy Patients</p>\n                        </div>\n                    </div>\n                    <!-- End Single Fun -->\n                </div>\n                <div class=\"col-lg-3 col-md-6 col-12\">\n                    <!-- Start Single Fun -->\n                    <div class=\"single-fun\">\n                        <i class=\"icofont icofont-table\"></i>\n                        <div class=\"content\">\n                            <span class=\"counter\">32</span>\n                            <p>Years of Experience</p>\n                        </div>\n                    </div>\n                    <!-- End Single Fun -->\n                </div>\n            </div>\n        </div>\n    </div>\n    <!--/ End Fun-facts -->  --}}\n    \n    <!-- Start Why choose -->\n    <section class=\"why-choose section\" id=\"apropos\">\n        <div class=\"container\">\n            <div class=\"row\">\n                <div class=\"col-lg-12\">\n                    <div class=\"section-title who\">\n                        <h2>Le mot du Président du Conseil d&apos;administration</h2>\n                        <img  class=\"mx-auto\" src=\"{{ asset('images/section-img.png') }}\" alt=\"#\">\n                        <p>La Mutuelle de la Police Nationale propose des services variés pour votre bien-être et celui de votre famille.</p>\n                    </div>\n                </div>\n            </div>\n            \n        \n            <div class=\"row\">\n                <div class=\"col-lg-12 col-12\">\n                    <div class=\"choose-content\">\n                        <div class=\"img-polaroid\">\n\n                            <img src=\"{{ asset('images/accueil/accueil8.jpg') }}\" class=\"\" alt=\"Photo PCA\">\n                            <figcaption class=\"photo-caption\">Président du Conseil d&apos;Administration</figcaption>\n                        </div>\n\n                        <h3 class=\" font-bold text-lg my-2\">Qui sommes-nous ?</h3>\n                        <p>\n                            La Mutuelle de la Police Nationale (MU-POL) qui a été portée sur les fonts baptismaux lors d’une Assemblée Générale constitutive le 19 novembre 2022 et lancée officiellement le 28 juillet 2023, constitue la plus vaste entreprise sociale portée par la Police Nationale. Je voudrais, à l’occasion du lancement de la présente page Facebook de la MU-POL, remercier les plus hautes autorités, le Ministre en charge de la sécurité, les Directeurs généraux de la Police Nationale, tout le Commandement de la Police Nationale et l’UNAPOL dont les efforts conjugués nous ont permis d’avoir ce bel instrument de solidarité permettant d’offrir une assurance santé et diverses prestations sociales aux policiers, au personnel civil de la Police Nationale et aux policiers à la retraite.\n                        </p>\n                        <p>\n                            Ma reconnaissance s’adresse particulièrement aux 4000 policiers et leurs familles qui ont adhéré à la Mutuelle, lesquels sont devenus nos premiers mutualistes et je les félicite pour leur esprit de solidarité. Je remercie aussi notre équipe, notamment les membres du Conseil d’Administration et son Secrétaire général, le Directeur général de la MU-POL et ses collaborateurs pour leur dévouement et leurs sacrifices pour assurer la bonne gouvernance de la Mutuelle et l’administration diligente des prestations. Nous sommes au service des policiers pour faciliter l’accès à des soins médicaux de qualité à coût social. La Mutuelle prend en charge vos soins médicaux à hauteur de 80% et développera d’autres types de prestations sociales qui participent au bien-être du policier. Le remboursement des frais médicaux a effectivement commencé le 1er juin 2024. La Mutuelle appartient à chaque policier et je vous invite à prendre possession de votre instrument en y adhérant massivement. Cette page Facebook a été créée afin de faire mieux connaitre la MU-POL et d’offrir aux mutualistes un espace de communication et de dialogue interactifs. Il ne nous reste plus qu’à souhaiter plein succès à la MU-POL avec la participation et la contribution de tout un chacun.\n                            Tous solidaires pour notre bien-être !\n                        </p>\n                        <!-- Signature -->\n                        <div class=\"signature\">\n                            <p><strong>Le Président du Conseil d’Administration</strong></p>\n                            <p><strong>Thierry Dofizouho TUINA</strong></p>\n                            <p>Inspecteur Général de Police</p>\n                            <p>Chevalier de l’Ordre de l’Etalon</p>\n                        </div>\n                    </div>\n                </div>\n            </div>\n            \n        </div>\n    </section>\n    <!--/ End Why choose -->\n\n    \n    {{--  <!-- Start Call to action -->\n    <section class=\"call-action overlay\" data-stellar-background-ratio=\"0.5\">\n        <div class=\"container\">\n            <div class=\"row\">\n                <div class=\"col-lg-12 col-md-12 col-12\">\n                    <div class=\"content\">\n                        <h2>Do you need Emergency Medical Care? Call @ 1234 56789</h2>\n                        <p>Lorem ipsum dolor sit amet, consectetur adipiscing elit. Quisque porttitor dictum turpis nec gravida.</p>\n                        <div class=\"button\">\n                            <a href=\"#\" class=\"btn\">Contact Now</a>\n                            <a href=\"#\" class=\"btn second\">Learn More<i class=\"fa fa-long-arrow-right\"></i></a>\n                        </div>\n                    </div>\n                </div>\n            </div>\n        </div>\n    </section>\n    <!--/ End Call to action -->  --}}\n    \n\n    <!-- Start service -->\n    <section class=\"services section\">\n        <div class=\"container\">\n            <div class=\"row\">\n                <div class=\"col-lg-12\">\n                    <div class=\"section-title\">\n                        <h2>Nous offrons différentes services de rembousements </h2>\n                        <img  class=\"mx-auto\" src=\"{{ asset('images/section-img.png') }}\" alt=\"#\">\n                        <p>La Mutuelle vous accompagne dans le remboursement de différentes prestations.</p>\n                    </div>\n                </div>\n            </div>\n            <div class=\"row\">\n              \n\n                @foreach ($types as $type)\n                    <div class=\"col-lg-4 col-md-6 col-12\">\n                        <!-- Start Single Service -->\n                        <div class=\"single-service\">\n                            @switch($type)\n                                @case('consultation')\n                                    <i class=\"icofont icofont-stethoscope\"></i>\n                                    <h4><a href=\"service-details.html\">Consultation</a></h4>\n                                    <p>{{ $descriptions['consultation'] }}</p>\n                                    @break\n                                @case('hospitalisation')\n                                    <i class=\"icofont icofont-hospital\"></i>\n                                    <h4><a href=\"service-details.html\">Hospitalisation</a></h4>\n                                    <p>{{ $descriptions['hospitalisation'] }}</p>\n                                    @break\n                                @case('radio')\n                                    <i class=\"icofont icofont-heart-alt\"></i>\n                                    <h4><a href=\"service-details.html\">Radiologie</a></h4>\n                                    <p>{{ $descriptions['radio'] }}</p>\n                                    @break\n                                @case('maternite')\n                                    <i class=\"icofont icofont-baby\"></i>\n                                    <h4><a href=\"service-details.html\">Maternité</a></h4>\n                                    <p>{{ $descriptions['maternite'] }}</p>\n                                    @break\n                                @case('allocation')\n                                    <i class=\"icofont icofont-money\"></i>\n                                    <h4><a href=\"service-details.html\">Allocations</a></h4>\n                                    <p>{{ $descriptions['allocation'] }}</p>\n                                    @break\n                                @case('analyse_biomedicale')\n                                    <i class=\"icofont icofont-test-tube\"></i>\n                                    <h4><a href=\"service-details.html\"> Analyses Biomedicales</a></h4>\n                                    <p>{{ $descriptions['analyse_biomedicale'] }}</p>\n                                    @break\n                                @case('pharmacie')\n                                    <i class=\"icofont icofont-medical-sign\"></i>\n                                    <h4><a href=\"service-details.html\">Pharmacie</a></h4>\n                                    <p>{{ $descriptions['pharmacie'] }}</p>\n                                    @break\n                                @case('optique')\n                                    <i class=\"icofont icofont-eye-alt\"></i>\n                                    <h4><a href=\"service-details.html\">Optique</a></h4>\n                                    <p>{{ $descriptions['optique'] }}</p>\n                                    @break\n                                @case('dentaire_auditif')\n                                    <i class=\"icofont icofont-tooth\"></i>\n                                    <h4><a href=\"service-details.html\">Soins dentaires et auditifs</a></h4>\n                                    <p>{{ $descriptions['dentaire_auditif'] }}</p>\n                                    @break\n                                \n                            @endswitch\n                        </div>\n                        <!-- End Single Service -->\n                    </div>\n                @endforeach\n\n\n            </div>\n        </div>\n    </section>\n    <!--/ End service -->\n    \n    <!-- Start Blog Area -->\n    <section class=\"blog section\" id=\"actualites\">\n        <div class=\"container\">\n            <div class=\"row\">\n                <div class=\"col-lg-12\">\n                    <div class=\"section-title\">\n                        <h2>La vie de la mutuelle.</h2>\n                        <img  class=\"mx-auto\" src=\"{{ asset('images/section-img.png') }}\" alt=\"#\">\n                        <p>Evènements récents organisés par la mutuelle.</p>\n                    </div>\n                </div>\n            </div>\n            <div class=\"row\">\n                <div class=\"col-lg-4 col-md-6 col-12\">\n                    <!-- Single Blog -->\n                    <div class=\"single-news\">\n                        <div class=\"news-head\">\n                            <img src=\"{{ asset('images/actualites/actualite3.jpg') }}\" alt=\"#\">\n                        </div>\n                        <div class=\"news-body\">\n                            <div class=\"news-content\">\n                                <div class=\"date\">27/09/2024</div>\n                                <h2><a href=\"blog-single.html\">Les femmes de la Police nationale discute du rôle et du leadership de la gente féminine dans l&apos;armée.</a></h2>\n                                {{-- <p class=\"text\">Lorem ipsum dolor a sit ameti, consectetur adipisicing elit, sed do eiusmod tempor incididunt sed do incididunt sed.</p> --}}\n                            </div>\n                        </div>\n                    </div>\n                    <!-- End Single Blog -->\n                </div>\n                <div class=\"col-lg-4 col-md-6 col-12\">\n                    <!-- Single Blog -->\n                    <div class=\"single-news\">\n                        <div class=\"news-head\">\n                            <img src=\"{{ asset('images/accueil/accueil3.jpg') }}\" alt=\"#\">\n                        </div>\n                        <div class=\"news-body\">\n                            <div class=\"news-content\">\n                                <div class=\"date\">15 Jul, 2020</div>\n                                <h2><a href=\"blog-single.html\">Top five way for solving teeth problems.</a></h2>\n                                <p class=\"text\">Lorem ipsum dolor a sit ameti, consectetur adipisicing elit, sed do eiusmod tempor incididunt sed do incididunt sed.</p>\n                            </div>\n                        </div>\n                    </div>\n                    <!-- End Single Blog -->\n                </div>\n                <div class=\"col-lg-4 col-md-6 col-12\">\n                    <!-- Single Blog -->\n                    <div class=\"single-news\">\n                        <div class=\"news-head\">\n                            <img src=\"{{ asset('images/accueil/accueil4.jpg') }}\" alt=\"#\">\n                        </div>\n                        <div class=\"news-body\">\n                            <div class=\"news-content\">\n                                <div class=\"date\">05 Jan, 2020</div>\n                                <h2><a href=\"blog-single.html\">We provide highly business soliutions.</a></h2>\n                                <p class=\"text\">Lorem ipsum dolor a sit ameti, consectetur adipisicing elit, sed do eiusmod tempor incididunt sed do incididunt sed.</p>\n                            </div>\n                        </div>\n                    </div>\n                    <!-- End Single Blog -->\n                </div>\n            </div>\n        </div>\n    </section>\n    <!-- End Blog Area -->\n    \n    \n      \n\n</x-guest-layout>\n\n"
        }
    ]
}