{
    "sourceFile": ".history/.lh/resources/views/pages/frontend/services/services.blade.php_20241128113607.json",
    "activeCommit": 0,
    "commits": [
        {
            "activePatchIndex": 0,
            "patches": [
                {
                    "date": 1732793925030,
                    "content": "Index: \n===================================================================\n--- \n+++ \n"
                }
            ],
            "date": 1732793925030,
            "name": "Commit-0",
            "content": "{\n    \"sourceFile\": \"resources/views/pages/frontend/services/services.blade.php\",\n    \"activeCommit\": 0,\n    \"commits\": [\n        {\n            \"activePatchIndex\": 0,\n            \"patches\": [\n                {\n                    \"date\": 1732791676732,\n                    \"content\": \"Index: \\n===================================================================\\n--- \\n+++ \\n\"\n                }\n            ],\n            \"date\": 1732791676732,\n            \"name\": \"Commit-0\",\n            \"content\": \"<x-guest-layout>\\r\\n    <x-preloader/>\\r\\n\\r\\n    <x-header-guest/>\\r\\n\\r\\n\\r\\n    \\r\\n    <!-- Single News -->\\r\\n\\t\\t<section class=\\\"news-single section\\\">\\r\\n\\t\\t\\t<div class=\\\"container\\\">\\r\\n\\t\\t\\t\\t<div class=\\\"row\\\">\\r\\n\\t\\t\\t\\t\\t<div class=\\\"col-lg-8 col-12\\\">\\r\\n\\t\\t\\t\\t\\t\\t<div class=\\\"row\\\">\\r\\n\\t\\t\\t\\t\\t\\t\\t<div class=\\\"col-12\\\">\\r\\n                                <div class=\\\"single-main \\\" contenteditable=\\\"true\\\">\\r\\n                                    <!-- News Head -->\\r\\n                                    <div class=\\\"news-head\\\">\\r\\n                                        <img src=\\\"{{ asset('images/services/service1.jpg') }}\\\" alt=\\\"Mutuelle Services Image\\\">\\r\\n                                    </div>\\r\\n                                    <!-- News Title -->\\r\\n                                    <h1 class=\\\"news-title !text-[#652E92]\\\">\\r\\n                                        Adhérer à la MU-POL : Bénéficiez d&apos;une Large Gamme de Prestations\\r\\n                                    </h1>\\r\\n                                    <!-- News Text -->\\r\\n\\r\\n                                    <div class=\\\"news-text\\\">\\r\\n                                        <p>En tant que membre de la MU-POL, vous avez accès à une gamme variée de prestations qui couvrent les principaux besoins en santé et bien-être. Découvrez ci-dessous les différents services remboursés :</p>\\r\\n                                    \\r\\n                                        <!-- Consultation -->\\r\\n                                        <h3 class=\\\"font-bold text-lg mt-4 mb-1 flex items-center\\\">\\r\\n                                            <i class=\\\"icofont icofont-stethoscope mr-2 p-2 bg-primary1 text-white font-bold rounded-md\\\"></i>\\r\\n                                            Consultation\\r\\n                                        </h3>\\r\\n                                        <p class=\\\" text-justify\\\">\\r\\n                                            {{__('La MU-POL propose un remboursement des frais de consultation médicale, permettant aux adhérents de se faire soigner par divers professionnels de santé, allant des généralistes aux spécialistes. Que vous ayez besoin d’un suivi médical régulier ou de soins pour une condition spécifique, vous pouvez consulter un médecin en toute tranquillité. En plus des consultations générales, la MU-POL couvre également les consultations spécialisées en cardiologie, dermatologie, pédiatrie, et bien d’autres, garantissant ainsi un accès étendu aux soins.')}}                                    </p>\\r\\n                                    \\r\\n                                        <!-- Hospitalization -->\\r\\n                                        <h3 class=\\\"font-bold text-lg mt-4 mb-1 flex items-center\\\">\\r\\n                                            <i class=\\\"icofont icofont-hospital mr-2 p-2 bg-primary1 text-white font-bold rounded-md\\\"></i>\\r\\n                                            Hospitalisation\\r\\n                                        </h3>\\r\\n                                        <p class=\\\" text-justify\\\">\\r\\n                                            {{__(' En cas d’hospitalisation, que ce soit pour une intervention chirurgicale, des soins intensifs ou un suivi post-opératoire, la MU-POL prend en charge une partie des frais, en fonction de la durée de votre séjour et de la nature des soins. Ce soutien financier couvre les frais de chambre, de soins infirmiers, et les traitements nécessaires. Que l’hospitalisation soit courte (moins de deux jours) ou prolongée (plus de deux semaines), la MU-POL accompagne les adhérents pour réduire les coûts liés aux soins hospitaliers.') }}\\r\\n                                        </p>\\r\\n                                    \\r\\n                                        <!-- Radiology -->\\r\\n                                        <h3 class=\\\"font-bold text-lg mt-4 mb-1 flex items-center\\\">\\r\\n                                            <i class=\\\"icofont icofont-heart-alt mr-2 p-2 bg-primary1 text-white font-bold rounded-md\\\"></i>\\r\\n                                            Radiologie\\r\\n                                        </h3>\\r\\n                                        <p class=\\\" text-justify\\\">\\r\\n                                            {{__('La radiologie est essentielle pour le diagnostic de nombreuses affections. La MU-POL couvre une gamme complète d\\\\'examens d\\\\'imagerie médicale, y compris les radiographies, les échographies, les IRM et les scanners. Ces examens sont pris en charge pour détecter des problèmes de santé spécifiques, permettant un diagnostic et un suivi rapide des pathologies. Que ce soit pour des examens de routine ou des tests plus approfondis, la couverture radiologique est conçue pour vous offrir une tranquillité d\\\\'esprit.') }}\\r\\n                                        </p>\\r\\n                                    \\r\\n                                        <!-- Maternity -->\\r\\n                                        <h3 class=\\\"font-bold text-lg mt-4 mb-1 flex items-center\\\">\\r\\n                                            <i class=\\\"icofont icofont-baby mr-2 p-2 bg-primary1 text-white font-bold rounded-md\\\"></i>\\r\\n                                            Maternité\\r\\n                                        </h3>\\r\\n                                        <p class=\\\" text-justify\\\">\\r\\n                                            {{__('La MU-POL offre un soutien accru aux futures mamans, prenant en charge les frais de suivi prénatal, des échographies de contrôle, et des frais liés à l’accouchement. Les adhérentes bénéficient d’un accompagnement complet pendant toute la période de grossesse, assurant la sécurité de la mère et de l’enfant. La couverture inclut également les frais en cas de complications médicales, garantissant un accès à des soins de qualité pour le bien-être de la mère et du bébé.') }}\\r\\n                                        </p>\\r\\n                                    \\r\\n                                        <!-- Pharmacy -->\\r\\n                                        <h3 class=\\\"font-bold text-lg mt-4 mb-1 flex items-center\\\">\\r\\n                                            <i class=\\\"icofont icofont-money mr-2 p-2 bg-primary1 text-white font-bold rounded-md\\\"></i>\\r\\n                                            Pharmacie\\r\\n                                        </h3>\\r\\n                                        <p class=\\\" text-justify\\\">\\r\\n                                            {{__('Les dépenses en médicaments peuvent rapidement s\\\\'accumuler, notamment en cas de traitement prolongé. La MU-POL prend en charge une partie des frais pharmaceutiques pour des médicaments prescrits, garantissant ainsi un accès facilité aux traitements nécessaires pour les adhérents et leurs ayants droit. Ce soutien s’applique aussi bien pour les traitements temporaires que pour les traitements de longue durée, allégeant le coût des soins au quotidien.') }}\\r\\n                                        </p>\\r\\n                                        \\r\\n                                        <!-- Biomedical Analysis -->\\r\\n                                        <h3 class=\\\"font-bold text-lg mt-4 mb-1 flex items-center\\\">\\r\\n                                            <i class=\\\"icofont icofont-laboratory mr-2 p-2 bg-primary1 text-white font-bold rounded-md\\\"></i>\\r\\n                                            Analyse Biomédicale\\r\\n                                        </h3>\\r\\n                                        <p class=\\\" text-justify\\\">\\r\\n                                            {{__('La MU-POL prend en charge les frais liés aux analyses biomédicales, essentielles pour le diagnostic et le suivi médical de nombreuses pathologies. Ces analyses comprennent les tests sanguins, les examens urinaires, les cultures microbiologiques, ainsi que d\\\\'autres examens spécialisés comme les bilans de santé réguliers, les dosages hormonaux ou les tests génétiques. Ces analyses sont cruciales pour identifier de manière précoce les maladies et affections, permettant une prise en charge rapide et adaptée.') }}\\r\\n                                        </p>\\r\\n\\r\\n                                        <!-- Optical Services -->\\r\\n                                        <h3 class=\\\"font-bold text-lg mt-4 mb-1 flex items-center\\\">\\r\\n                                            <i class=\\\"icofont icofont-eye-alt mr-2 p-2 bg-primary1 text-white font-bold rounded-md\\\"></i>\\r\\n                                            Optique\\r\\n                                        </h3>\\r\\n                                        <p class=\\\" text-justify\\\">\\r\\n                                            {{__('La santé visuelle est primordiale, et la MU-POL s’engage à rembourser une partie des frais liés aux soins optiques. Que ce soit pour des examens de la vue, des lunettes de correction, ou des lentilles, les adhérents peuvent bénéficier d’un soutien financier pour leurs dépenses en optique. Ce remboursement permet de maintenir une bonne vision, essentielle pour la qualité de vie au quotidien.') }}\\r\\n                                        </p>\\r\\n                                    \\r\\n                                        <!-- Dental & Auditory Services -->\\r\\n                                        <h3 class=\\\"font-bold text-lg mt-4 mb-1 flex items-center\\\">\\r\\n                                            <i class=\\\"icofont icofont-tooth mr-2 p-2 bg-primary1 text-white font-bold rounded-md\\\"></i>\\r\\n                                            Soins Dentaires & Auditifs\\r\\n                                        </h3>\\r\\n                                        <p class=\\\" text-justify\\\">\\r\\n                                            {{__('La MU-POL prend en charge les soins dentaires et auditifs, des contrôles de routine aux soins plus spécifiques, tels que les prothèses dentaires et auditives. Ces services incluent des consultations de suivi, des soins de prévention, et des traitements en cas de problèmes dentaires ou auditifs. Ainsi, les adhérents peuvent maintenir une bonne hygiène bucco-dentaire et auditive, indispensable pour la santé générale.') }}\\r\\n                                        </p>\\r\\n                                    \\r\\n                                        <!-- Allocation -->\\r\\n                                        <h3 class=\\\"font-bold text-lg mt-4 mb-1 flex items-center\\\">\\r\\n                                            <i class=\\\"icofont icofont-money mr-2 p-2 bg-primary1 text-white font-bold rounded-md\\\"></i>\\r\\n                                            Allocation\\r\\n                                        </h3>\\r\\n                                        <p class=\\\" text-justify\\\">\\r\\n                                            {{__('En cas de situation particulière (invalidité, décès d\\\\'un adhérent ou d\\\\'un ayant droit), la MU-POL offre des allocations spécifiques pour aider financièrement les familles dans ces moments difficiles. Cette allocation peut aussi inclure un secours médical pour des traitements exceptionnels ou non couverts. Les adhérents peuvent compter sur cette assistance pour alléger les coûts imprévus liés à des conditions particulières.') }}\\r\\n                                        </p>\\r\\n\\r\\n                                        <blockquote class=\\\" mt-4 bg-primary1\\\">\\r\\n                                            <p>« Adhérer à la MU-POL, c&apos;est assurer sa santé et celle de ses proches avec des prestations diversifiées et adaptées à tous les besoins. »</p>\\r\\n                                        </blockquote>\\r\\n                                    \\r\\n                                        {{--  <div class=\\\"image-gallery mt-4\\\">\\r\\n                                            <div class=\\\"row\\\">\\r\\n                                                <div class=\\\"col-lg-6 col-md-6 col-12\\\">\\r\\n                                                    <div class=\\\"single-image\\\">\\r\\n                                                        <img src=\\\"{{ asset('images/accueil/accueil6.jpg') }}\\\" alt=\\\"Service Image 1\\\">\\r\\n                                                    </div>\\r\\n                                                </div>\\r\\n                                                <div class=\\\"col-lg-6 col-md-6 col-12\\\">\\r\\n                                                    <div class=\\\"single-image\\\">\\r\\n                                                        <img src=\\\"{{ asset('images/accueil/accueil4.jpg') }}\\\" alt=\\\"Service Image 2\\\">\\r\\n                                                    </div>\\r\\n                                                </div>\\r\\n                                            </div>\\r\\n                                        </div>  --}}\\r\\n                                    </div>\\r\\n                                    \\r\\n                                </div>\\r\\n                            </div>\\r\\n                            \\r\\n\\t\\t\\t\\t\\t\\t\\t\\r\\n\\t\\t\\t\\t\\t\\t</div>\\r\\n\\t\\t\\t\\t\\t</div>\\r\\n\\t\\t\\t\\t\\t<div class=\\\"col-lg-4 col-12\\\">\\r\\n\\t\\t\\t\\t\\t\\t<div class=\\\"main-sidebar\\\">\\r\\n\\t\\t\\t\\t\\t\\t\\t<!-- Single Widget -->\\r\\n\\t\\t\\t\\t\\t\\t\\t<div class=\\\"single-widget search\\\">\\r\\n\\t\\t\\t\\t\\t\\t\\t\\t<div class=\\\"form\\\">\\r\\n\\t\\t\\t\\t\\t\\t\\t\\t\\t<input type=\\\"text\\\" id=\\\"findField\\\" placeholder=\\\"Rechercher...\\\">\\r\\n\\t\\t\\t\\t\\t\\t\\t\\t\\t<button class=\\\"button bg-primary1\\\" href=\\\"#\\\" onclick=\\\"search();\\\"><i class=\\\"fa fa-search\\\"></i></button>\\r\\n\\t\\t\\t\\t\\t\\t\\t\\t</div>\\r\\n                                \\r\\n                                {{--  <button onclick=\\\"removeHightlight();\\\">removeHightlight</button>  --}}  \\r\\n                                <script>\\r\\n                                    function findNext(str) {\\r\\n\\r\\n                                        if (str == \\\"\\\") {\\r\\n                                            alert(\\\"Entrez un mot !\\\");\\r\\n                                            return;\\r\\n                                        }\\r\\n                                        return window.find(str);\\r\\n                                    }\\r\\n                                    \\r\\n                                    function search() {\\r\\n                                        console.clear();    \\r\\n                                        removeHightlight();\\r\\n                                        var sel = window.getSelection();\\r\\n                                        sel.removeAllRanges();\\r\\n                                        var str = document.getElementById(\\\"findField\\\").value;\\r\\n                                        document.getElementById(\\\"findField\\\").value = \\\"\\\";\\r\\n                                        console.log(\\\"Début de la recherche du mot : \\\", str);\\r\\n                                    \\r\\n                                        while (findNext(str)) {\\r\\n                                    \\r\\n                                            var range = sel.getRangeAt(0);        \\r\\n                                            var hightlightSpan = document.createElement(\\\"span\\\");\\r\\n                                            hightlightSpan.className = \\\"hightlightClass\\\";\\r\\n                                            hightlightSpan.appendChild(range.extractContents());\\r\\n                                            range.insertNode(hightlightSpan);\\r\\n                                        }\\r\\n                                        console.log(\\\"Fin de la recherche\\\");\\r\\n                                        sel.removeAllRanges();\\r\\n                                        document.getElementById(\\\"findField\\\").value = str;\\r\\n                                    }\\r\\n                                    \\r\\n                                    function removeHightlight() {\\r\\n                                    \\r\\n                                        var hightlightSpanTab = document.getElementsByClassName(\\\"hightlightClass\\\");\\r\\n                                        \\r\\n                                        while(hightlightSpanTab.length) {\\r\\n                                            var parent = hightlightSpanTab[0].parentNode;\\r\\n                                            while( hightlightSpanTab[0].firstChild ) {\\r\\n                                                parent.insertBefore(  hightlightSpanTab[0].firstChild, hightlightSpanTab[0] );\\r\\n                                            }\\r\\n                                             parent.removeChild( hightlightSpanTab[0] );\\r\\n                                        }    \\r\\n                                    }\\r\\n                                    \\r\\n                                </script>\\r\\n                               \\r\\n\\t\\t\\t\\t\\t\\t\\t</div>\\r\\n\\t\\t\\t\\t\\t\\t\\t<!--/ End Single Widget -->\\r\\n\\t\\t\\t\\t\\t\\t\\t<!-- Single Widget -->\\r\\n\\t\\t\\t\\t\\t\\t\\t<!-- Catégories des services -->\\r\\n                            <div class=\\\"single-widget category\\\">\\r\\n                                <h3 class=\\\"title\\\">Catégories de services</h3>\\r\\n                                <ul class=\\\"category-list\\\">\\r\\n                                    <li><a href=\\\"#\\\">Consultation</a></li>\\r\\n                                    <li><a href=\\\"#\\\">Hospitalisation</a></li>\\r\\n                                    <li><a href=\\\"#\\\">Radio</a></li>\\r\\n                                    <li><a href=\\\"#\\\">Maternité</a></li>\\r\\n                                    <li><a href=\\\"#\\\">Pharmacie</a></li>\\r\\n                                    <li><a href=\\\"#\\\">Optique</a></li>\\r\\n                                    <li><a href=\\\"#\\\">Dentaire & Auditif</a></li>\\r\\n                                    \\r\\n                                </ul>\\r\\n                            </div>\\r\\n\\t\\t\\t\\t\\t\\t\\t<!--/ End Single Widget -->\\r\\n\\t\\t\\t\\t\\t\\t\\t<!-- Single Widget -->\\r\\n\\t\\t\\t\\t\\t\\t\\t<div class=\\\"single-widget recent-post\\\">\\r\\n\\t\\t\\t\\t\\t\\t\\t\\t<h3 class=\\\"title\\\">Actualités récentes</h3>\\r\\n\\t\\t\\t\\t\\t\\t\\t\\t<!-- Single Post -->\\r\\n\\t\\t\\t\\t\\t\\t\\t\\t<div class=\\\"single-post\\\">\\r\\n\\t\\t\\t\\t\\t\\t\\t\\t\\t<div class=\\\"image\\\">\\r\\n                                        <img src=\\\"{{ asset('images/accueil/accueil6.jpg') }}\\\" alt=\\\"Service Image 1\\\">\\r\\n\\t\\t\\t\\t\\t\\t\\t\\t\\t</div>\\r\\n\\t\\t\\t\\t\\t\\t\\t\\t\\t<div class=\\\"content\\\">\\r\\n\\t\\t\\t\\t\\t\\t\\t\\t\\t\\t<h5><a href=\\\"#\\\">We have annnocuced our new product.</a></h5>\\r\\n\\t\\t\\t\\t\\t\\t\\t\\t\\t\\t<ul class=\\\"comment\\\">\\r\\n\\t\\t\\t\\t\\t\\t\\t\\t\\t\\t\\t<li><i class=\\\"fa fa-calendar\\\" aria-hidden=\\\"true\\\"></i>Jan 11, 2020</li>\\r\\n\\t\\t\\t\\t\\t\\t\\t\\t\\t\\t\\t<li><i class=\\\"fa fa-commenting-o\\\" aria-hidden=\\\"true\\\"></i>35</li>\\r\\n\\t\\t\\t\\t\\t\\t\\t\\t\\t\\t</ul>\\r\\n\\t\\t\\t\\t\\t\\t\\t\\t\\t</div>\\r\\n\\t\\t\\t\\t\\t\\t\\t\\t</div>\\r\\n\\t\\t\\t\\t\\t\\t\\t\\t<!-- End Single Post -->\\r\\n\\t\\t\\t\\t\\t\\t\\t\\t<!-- Single Post -->\\r\\n\\t\\t\\t\\t\\t\\t\\t\\t<div class=\\\"single-post\\\">\\r\\n\\t\\t\\t\\t\\t\\t\\t\\t\\t<div class=\\\"image\\\">\\r\\n                                        <img src=\\\"{{ asset('images/accueil/accueil6.jpg') }}\\\" alt=\\\"Service Image 1\\\">\\r\\n\\t\\t\\t\\t\\t\\t\\t\\t\\t</div>\\r\\n\\t\\t\\t\\t\\t\\t\\t\\t\\t<div class=\\\"content\\\">\\r\\n\\t\\t\\t\\t\\t\\t\\t\\t\\t\\t<h5><a href=\\\"#\\\">Top five way for solving teeth problems.</a></h5>\\r\\n\\t\\t\\t\\t\\t\\t\\t\\t\\t\\t<ul class=\\\"comment\\\">\\r\\n\\t\\t\\t\\t\\t\\t\\t\\t\\t\\t\\t<li><i class=\\\"fa fa-calendar\\\" aria-hidden=\\\"true\\\"></i>Mar 05, 2019</li>\\r\\n\\t\\t\\t\\t\\t\\t\\t\\t\\t\\t\\t<li><i class=\\\"fa fa-commenting-o\\\" aria-hidden=\\\"true\\\"></i>59</li>\\r\\n\\t\\t\\t\\t\\t\\t\\t\\t\\t\\t</ul>\\r\\n\\t\\t\\t\\t\\t\\t\\t\\t\\t</div>\\r\\n\\t\\t\\t\\t\\t\\t\\t\\t</div>\\r\\n\\t\\t\\t\\t\\t\\t\\t\\t<!-- End Single Post -->\\r\\n\\t\\t\\t\\t\\t\\t\\t\\t<!-- Single Post -->\\r\\n\\t\\t\\t\\t\\t\\t\\t\\t<div class=\\\"single-post\\\">\\r\\n\\t\\t\\t\\t\\t\\t\\t\\t\\t<div class=\\\"image\\\">\\r\\n                                        <img src=\\\"{{ asset('images/accueil/accueil4.jpg') }}\\\" alt=\\\"Service Image 1\\\">\\r\\n\\t\\t\\t\\t\\t\\t\\t\\t\\t</div>\\r\\n\\t\\t\\t\\t\\t\\t\\t\\t\\t<div class=\\\"content\\\">\\r\\n\\t\\t\\t\\t\\t\\t\\t\\t\\t\\t<h5><a href=\\\"#\\\">We provide highly business soliutions.</a></h5>\\r\\n\\t\\t\\t\\t\\t\\t\\t\\t\\t\\t<ul class=\\\"comment\\\">\\r\\n\\t\\t\\t\\t\\t\\t\\t\\t\\t\\t\\t<li><i class=\\\"fa fa-calendar\\\" aria-hidden=\\\"true\\\"></i>June 09, 2019</li>\\r\\n\\t\\t\\t\\t\\t\\t\\t\\t\\t\\t\\t<li><i class=\\\"fa fa-commenting-o\\\" aria-hidden=\\\"true\\\"></i>44</li>\\r\\n\\t\\t\\t\\t\\t\\t\\t\\t\\t\\t</ul>\\r\\n\\t\\t\\t\\t\\t\\t\\t\\t\\t</div>\\r\\n\\t\\t\\t\\t\\t\\t\\t\\t</div>\\r\\n\\t\\t\\t\\t\\t\\t\\t\\t<!-- End Single Post -->\\r\\n\\t\\t\\t\\t\\t\\t\\t</div>\\r\\n\\t\\t\\t\\t\\t\\t\\t<!--/ End Single Widget -->\\r\\n\\t\\t\\t\\t\\t\\t\\t<!-- Single Widget -->\\r\\n\\t\\t\\t\\t\\t\\t\\t<!--/ End Single Widget -->\\r\\n\\t\\t\\t\\t\\t\\t\\t<!-- Single Widget -->\\r\\n\\t\\t\\t\\t\\t\\t\\t<div class=\\\"single-widget side-tags\\\">\\r\\n                                <h3 class=\\\"title\\\">Tags</h3>\\r\\n                                <ul class=\\\"tag\\\">\\r\\n                                    <li><a href=\\\"#\\\">santé</a></li>\\r\\n                                    <li><a href=\\\"#\\\">consultation</a></li>\\r\\n                                    <li><a href=\\\"#\\\">hospitalisation</a></li>\\r\\n                                    <li><a href=\\\"#\\\">analyse biomédicale</a></li>\\r\\n                                    <li><a href=\\\"#\\\">pharmacie</a></li>\\r\\n                                    <li><a href=\\\"#\\\">optique</a></li>\\r\\n                                </ul>\\r\\n                            </div>\\r\\n\\t\\t\\t\\t\\t\\t\\t<!--/ End Single Widget -->\\r\\n\\t\\t\\t\\t\\t\\t</div>\\r\\n\\t\\t\\t\\t\\t</div>\\r\\n\\t\\t\\t\\t</div>\\r\\n\\t\\t\\t</div>\\r\\n\\t\\t</section>\\r\\n\\t<!--/ End Single News -->\\r\\n      \\r\\n\\r\\n</x-guest-layout>\\r\\n\"\n        }\n    ]\n}"
        }
    ]
}